{
  "products": [
    {
      "id": "f5edd2e5-1494-41e7-bc58-b21acea17db1",
      "name": "Bike",
      "description": "The beautiful range of Apple Naturalé that has an exciting mix of natural ingredients. With the Goodness of 100% Natural Ingredients"
    },
    {
      "id": "7ca963d7-71c3-44eb-a14c-80a0c23986cb",
      "name": "Bike",
      "description": "Andy shoes are designed to keeping in mind durability as well as trends, the most stylish range of shoes & sandals"
    },
    {
      "id": "a05c039f-3141-408e-95e3-0cfa4e7b2179",
      "name": "Car",
      "description": "The automobile layout consists of a front-engine design, with transaxle-type transmissions mounted at the rear of the engine and four wheel drive"
    },
    {
      "id": "35f0644c-8230-4450-8418-6f0b939025aa",
      "name": "Chair",
      "description": "Ergonomic executive chair upholstered in bonded black leather and PVC padded seat and back for all-day comfort and support"
    },
    {
      "id": "1703f9d5-d68f-4e54-b2a6-2dd4065d2969",
      "name": "Keyboard",
      "description": "The automobile layout consists of a front-engine design, with transaxle-type transmissions mounted at the rear of the engine and four wheel drive"
    },
    {
      "id": "25244792-149f-4c9a-aa0e-a0d4d223a987",
      "name": "Cheese",
      "description": "The Apollotech B340 is an affordable wireless mouse with reliable connectivity, 12 months battery life and modern design"
    },
    {
      "id": "57881032-236e-465b-9eff-45194eefddfb",
      "name": "Bacon",
      "description": "Carbonite web goalkeeper gloves are ergonomically designed to give easy fit"
    },
    {
      "id": "edbccbb4-9135-4ece-b2e7-40ba2bc9decd",
      "name": "Fish",
      "description": "New ABC 13 9370, 13.3, 5th Gen CoreA5-8250U, 8GB RAM, 256GB SSD, power UHD Graphics, OS 10 Home, OS Office A & J 2016"
    },
    {
      "id": "d755ce6e-f300-490d-a2ba-7175890a1ff5",
      "name": "Chips",
      "description": "The slim & simple Maple Gaming Keyboard from Dev Byte comes with a sleek body and 7- Color RGB LED Back-lighting for smart functionality"
    },
    {
      "id": "32bd0057-97ae-447c-ba66-6b865d9f8014",
      "name": "Bacon",
      "description": "The slim & simple Maple Gaming Keyboard from Dev Byte comes with a sleek body and 7- Color RGB LED Back-lighting for smart functionality"
    }
  ]
}
